[
  {
    "ocorrido": "DSADASDA",
    "endereco": "Rua Ministro Nélson Hungria, Boa Viagem, Recife, Pernambuco"
  },
  {
    "ocorrido": "asdasdasdas",
    "endereco": "Avenida Engenheiro Domingos Ferreira, Boa Viagem, Recife, Pernambuco"
  },
  {
    "ocorrido": "fdgfdrtg",
    "endereco": "Rua Maria Carolina, Boa Viagem, Recife, Pernambuco"
  },
  {
    "ocorrido": "cbcbbvvcvb",
    "endereco": "Avenida Conselheiro Aguiar, Boa Viagem, Recife, Pernambuco"
  },
  {
    "ocorrido": "asdasda",
    "endereco": ", Boa Viagem, Recife, Pernambuco"
  },
  {
    "ocorrido": "dsadasdasdasdas",
    "endereco": "Rua Antônio Falcão, Boa Viagem, Recife, Pernambuco"
  },
  {
    "ocorrido": "asdasdasdas",
    "endereco": "Rua Tenente João Cícero, Boa Viagem, Recife, Pernambuco"
  },
  {
    "ocorrido": ".çç[~´.pççp",
    "endereco": "Rua Ministro Nélson Hungria, Boa Viagem, Recife, Pernambuco"
  }
]